tpg_256a_pressure_monitor/Daemon.py
tpg_256a_pressure_monitor/Monitor.py
tpg_256a_pressure_monitor/TPG_256A.py
tpg_256a_pressure_monitor/TPG_256A_Pressure_Monitor.py
tpg_256a_pressure_monitor/__init__.py
tpg_256a_pressure_monitor/__main__.py
tpg_256a_pressure_monitor/__project__.py
tpg_256a_pressure_monitor/tpg_256a_pressure_monitor.py
tpg_256a_pressure_monitor-0.3.0.dist-info/LICENSE.md
tpg_256a_pressure_monitor-0.3.0.dist-info/METADATA
tpg_256a_pressure_monitor-0.3.0.dist-info/WHEEL
tpg_256a_pressure_monitor-0.3.0.dist-info/entry_points.txt
tpg_256a_pressure_monitor-0.3.0.dist-info/top_level.txt
tpg_256a_pressure_monitor-0.3.0.dist-info/RECORD
