Metadata-Version: 2.1
Name: tpg-256a-pressure-monitor
Version: 0.3.0
Summary: Readout software for the Pfeiffer TPG-256A Pressure Controller
Home-page: https://gitlab.ethz.ch/exotic-matter/cw-beam/maxigauge-pressure-monitor
Author: Carlos Vigo
Author-email: <carlosv@phys.ethz.ch>
License: GPLv3
Platform: UNKNOWN
Classifier: Programming Language :: Python :: 3.6
Classifier: License :: OSI Approved :: GNU General Public License v3 (GPLv3)
Classifier: Operating System :: POSIX :: Linux
Requires-Python: >=3.6
Requires-Dist: lab-utils
Requires-Dist: pyserial
Requires-Dist: zc.lockfile
Provides-Extra: dev
Requires-Dist: flake8 ; extra == 'dev'
Requires-Dist: pytest ; extra == 'dev'
Provides-Extra: docs
Requires-Dist: recommonmark ; extra == 'docs'
Requires-Dist: sphinx ; extra == 'docs'
Requires-Dist: sphinx-paramlinks ; extra == 'docs'
Requires-Dist: sphinx-rtd-theme ; extra == 'docs'
Requires-Dist: wheel ; extra == 'docs'
